odoo/addons/l10n_us_check_writing_address/README.rst
odoo/addons/l10n_us_check_writing_address/__init__.py
odoo/addons/l10n_us_check_writing_address/__manifest__.py
odoo/addons/l10n_us_check_writing_address/data/account_payment_check_report_data.xml
odoo/addons/l10n_us_check_writing_address/i18n/l10n_us_check_writing_address.pot
odoo/addons/l10n_us_check_writing_address/models/__init__.py
odoo/addons/l10n_us_check_writing_address/models/res_partner.py
odoo/addons/l10n_us_check_writing_address/readme/CONFIGURE.rst
odoo/addons/l10n_us_check_writing_address/readme/CONTRIBUTORS.rst
odoo/addons/l10n_us_check_writing_address/readme/CREDITS.rst
odoo/addons/l10n_us_check_writing_address/readme/DESCRIPTION.rst
odoo/addons/l10n_us_check_writing_address/readme/USAGE.rst
odoo/addons/l10n_us_check_writing_address/report/__init__.py
odoo/addons/l10n_us_check_writing_address/report/account_check_writing_report.xml
odoo/addons/l10n_us_check_writing_address/report/check_print.py
odoo/addons/l10n_us_check_writing_address/report/report_check_base_bottom.xml
odoo/addons/l10n_us_check_writing_address/report/report_check_base_middle.xml
odoo/addons/l10n_us_check_writing_address/report/report_check_base_top.xml
odoo/addons/l10n_us_check_writing_address/static/description/icon.png
odoo/addons/l10n_us_check_writing_address/static/description/index.html
odoo11_addon_l10n_us_check_writing_address-11.0.1.0.0.99.dev5.dist-info/METADATA
odoo11_addon_l10n_us_check_writing_address-11.0.1.0.0.99.dev5.dist-info/WHEEL
odoo11_addon_l10n_us_check_writing_address-11.0.1.0.0.99.dev5.dist-info/top_level.txt
odoo11_addon_l10n_us_check_writing_address-11.0.1.0.0.99.dev5.dist-info/RECORD
